FaaSr_py/FaaSr.schema.json
FaaSr_py/__init__.py
FaaSr_py/client/__init__.py
FaaSr_py/client/py_client_stubs.py
FaaSr_py/client/py_user_func_entry.py
FaaSr_py/client/r_client_stubs.R
FaaSr_py/client/r_func_helper.R
FaaSr_py/client/r_user_func_entry.R
FaaSr_py/config/__init__.py
FaaSr_py/config/config.json
FaaSr_py/config/debug_config.py
FaaSr_py/config/logger_classes.py
FaaSr_py/config/s3_log_handler.py
FaaSr_py/config/s3_log_sender.py
FaaSr_py/engine/__init__.py
FaaSr_py/engine/executor.py
FaaSr_py/engine/faasr_payload.py
FaaSr_py/engine/scheduler.py
FaaSr_py/helpers/__init__.py
FaaSr_py/helpers/exceptions.py
FaaSr_py/helpers/faasr_lock.py
FaaSr_py/helpers/faasr_start_invoke_helper.py
FaaSr_py/helpers/gcp_auth.py
FaaSr_py/helpers/graph_functions.py
FaaSr_py/helpers/py_func_helper.py
FaaSr_py/helpers/rank.py
FaaSr_py/helpers/s3_helper_functions.py
FaaSr_py/helpers/slurm_helper.py
FaaSr_py/s3_api/__init__.py
FaaSr_py/s3_api/delete_file.py
FaaSr_py/s3_api/get_file.py
FaaSr_py/s3_api/get_folder_list.py
FaaSr_py/s3_api/get_s3_creds.py
FaaSr_py/s3_api/log.py
FaaSr_py/s3_api/put_file.py
FaaSr_py/server/__init__.py
FaaSr_py/server/faasr_server.py
FaaSr_py/testing/__init__.py
FaaSr_py/testing/local_func.py
FaaSr_py/testing/put_and_delete.py
FaaSr_py/testing/s3benchmark.py
FaaSr_py/testing/workflow_test.py
FaaSr_py/testing/workflow_test_entry.py
faasr_py-0.1.11.dist-info/licenses/LICENSE
faasr_py-0.1.11.dist-info/METADATA
faasr_py-0.1.11.dist-info/WHEEL
faasr_py-0.1.11.dist-info/top_level.txt
faasr_py-0.1.11.dist-info/RECORD
